{"assets":{"085A49673D7C8714419088366BDA5601":{"type":"texture","index":4,"assetRequest":{"type":"slide","state":"contents","slide":"none"},"url":{"native":"assets\/7008FBD6-A027-490C-BC22-21438584B063.pdf"},"width":1024,"height":768},"A4964A8E03089811758250A7FBDF6457":{"type":"texture","index":1,"assetRequest":{"type":"slide","state":"contents","slide":"none"},"url":{"native":"assets\/7008FBD6-A027-490C-BC22-21438584B063.pdf"},"width":159,"height":32},"DB8451458D98EFA7506DBEBC2B1323F0":{"type":"texture","index":0,"assetRequest":{"type":"slide","state":"contents","slide":"none"},"url":{"native":"assets\/7008FBD6-A027-490C-BC22-21438584B063.pdf"},"width":1024,"height":768},"D381CA1634311E8A93805CE60B7148BA":{"type":"texture","index":2,"assetRequest":{"type":"slide","state":"contents","slide":"none"},"url":{"native":"assets\/7008FBD6-A027-490C-BC22-21438584B063.pdf"},"width":319,"height":30},"6653C94945E0E083797A02191B1D1321":{"type":"texture","index":3,"assetRequest":{"type":"slide","state":"contents","slide":"none"},"url":{"native":"assets\/7008FBD6-A027-490C-BC22-21438584B063.pdf"},"width":752,"height":64}},"events":[{"effects":[{"beginTime":0,"baseLayer":{"animations":[],"initialState":{"affineTransform":[1,0,0,1,0,0],"masksToBounds":false,"rotation":0,"scale":1,"position":{"pointX":508.36999797821045,"pointY":375},"width":159,"sublayerTransform":[1,0,0,0,0,1,0,0,0,0,1,0,0,0,0,1],"contentsRect":{"y":0,"x":0,"width":1,"height":1},"opacity":1,"edgeAntialiasingMask":251658240,"height":32,"hidden":false,"anchorPoint":{"pointX":0.5,"pointY":0.5}},"objectID":"3B454D10-C834-4888-914B-9641B0174997","layers":[{"animations":[],"initialState":{"affineTransform":[1,0,0,1,0,0],"masksToBounds":false,"rotation":0,"scale":1,"position":{"pointX":83.130002021789551,"pointY":25},"width":159,"sublayerTransform":[1,0,0,0,0,1,0,0,0,0,1,-0.00049229876906403734,0,0,0,1],"contentsRect":{"y":0,"x":0,"width":1,"height":1},"opacity":1,"edgeAntialiasingMask":251658240,"height":32,"hidden":false,"anchorPoint":{"pointX":0.52283020139490288,"pointY":0.78125}},"layers":[{"animations":[{"timeOffset":0,"beginTime":1e-100,"repeatCount":0,"animations":[{"timeOffset":0,"from":{"scalar":0},"beginTime":0,"repeatCount":0,"fillMode":"both","duration":0.75,"autoreverses":false,"timingFunction":"EaseInEaseOut","property":"opacity","to":{"scalar":1}},{"timeOffset":0,"timingFunctions":[{"timingFunction":"EaseIn"},{"timingFunction":"custom","timingControlPoint1y":0,"timingControlPoint2x":0.57624423503875732,"timingControlPoint1x":0,"timingControlPoint2y":1},{"timingFunction":"custom","timingControlPoint1y":0.10000000149011612,"timingControlPoint2x":1,"timingControlPoint1x":0.25,"timingControlPoint2y":1}],"beginTime":0,"values":[{"scalar":0.001},{"scalar":1.125},{"scalar":0.95199999999999996},{"scalar":0.99999999999999989}],"repeatCount":0,"fillMode":"removed","property":"transform.scale.xy","autoreverses":false,"duration":0.75,"keyTimes":[0,0.42999999999999999,0.66700000000000004,1]},{"timeOffset":0,"from":{"scalar":false},"beginTime":0.0001,"repeatCount":0,"fillMode":"forwards","property":"hidden","autoreverses":false,"duration":0.74990000000000001,"to":{"scalar":false}}],"fillMode":"both","autoreverses":false,"duration":0.75}],"layers":[],"texturedRectangle":{"singleTextureOpacity":1,"textXHeight":0.5625,"textBaseline":0.83749935403466225,"isBackgroundTexture":true,"isVerticalText":false,"textColor":[0.9999966025352478,0.99999994039535522,0.99999994039535522,1],"textureType":6},"initialState":{"affineTransform":[1,0,0,1,0,0],"masksToBounds":false,"rotation":0,"scale":1,"position":{"pointX":82.630002021789551,"pointY":25},"width":159,"sublayerTransform":[1,0,0,0,0,1,0,0,0,0,1,0,0,0,0,1],"contentsRect":{"y":0,"x":0,"width":1,"height":1},"opacity":1,"edgeAntialiasingMask":0,"height":32,"hidden":true,"anchorPoint":{"pointX":0.5,"pointY":0.5}},"texture":"A4964A8E03089811758250A7FBDF6457"}]}]},"effects":[],"duration":0.75,"type":"buildIn","attributes":{"direction":0},"name":"apple:bc-pop","objectID":"3B454D10-C834-4888-914B-9641B0174997"}],"automaticPlay":true,"hyperlinks":[],"accessibility":[],"baseLayer":{"animations":[],"initialState":{"affineTransform":[1,0,0,1,0,0],"masksToBounds":false,"rotation":0,"scale":1,"position":{"pointX":512,"pointY":384},"width":1024,"sublayerTransform":[1,0,0,0,0,1,0,0,0,0,1,0,0,0,0,1],"contentsRect":{"y":0,"x":0,"width":1,"height":1},"opacity":1,"edgeAntialiasingMask":251658240,"height":768,"hidden":false,"anchorPoint":{"pointX":0.5,"pointY":0.5}},"layers":[{"animations":[],"initialState":{"affineTransform":[1,0,0,1,0,0],"masksToBounds":false,"rotation":0,"scale":1,"position":{"pointX":512,"pointY":384},"width":1024,"sublayerTransform":[1,0,0,0,0,1,0,0,0,0,1,0,0,0,0,1],"contentsRect":{"y":0,"x":0,"width":1,"height":1},"opacity":1,"edgeAntialiasingMask":251658240,"height":768,"hidden":false,"anchorPoint":{"pointX":0.5,"pointY":0.5}},"layers":[{"animations":[],"initialState":{"affineTransform":[1,0,0,1,0,0],"masksToBounds":false,"rotation":0,"scale":1,"position":{"pointX":512,"pointY":384},"width":1024,"sublayerTransform":[1,0,0,0,0,1,0,0,0,0,1,0,0,0,0,1],"contentsRect":{"y":0,"x":0,"width":1,"height":1},"opacity":1,"edgeAntialiasingMask":251658240,"height":768,"hidden":false,"anchorPoint":{"pointX":0.5,"pointY":0.5}},"layers":[{"animations":[],"layers":[],"texturedRectangle":{"isBackgroundTexture":true,"singleTextureOpacity":1,"textureType":1,"textBaseline":0,"textXHeight":0,"isVerticalText":false},"initialState":{"affineTransform":[1,0,0,1,0,0],"masksToBounds":false,"rotation":0,"scale":1,"position":{"pointX":512,"pointY":384},"width":1024,"sublayerTransform":[1,0,0,0,0,1,0,0,0,0,1,0,0,0,0,1],"contentsRect":{"y":0,"x":0,"width":1,"height":1},"opacity":1,"edgeAntialiasingMask":0,"height":768,"hidden":false,"anchorPoint":{"pointX":0.5,"pointY":0.5}},"texture":"DB8451458D98EFA7506DBEBC2B1323F0"}]}]},{"animations":[],"initialState":{"affineTransform":[1,0,0,1,0,0],"masksToBounds":false,"rotation":0,"scale":1,"position":{"pointX":512,"pointY":384},"width":1024,"sublayerTransform":[1,0,0,0,0,1,0,0,0,0,1,0,0,0,0,1],"contentsRect":{"y":0,"x":0,"width":1,"height":1},"opacity":1,"edgeAntialiasingMask":251658240,"height":768,"hidden":false,"anchorPoint":{"pointX":0.5,"pointY":0.5}},"layers":[{"animations":[],"initialState":{"affineTransform":[1,0,0,1,0,0],"masksToBounds":false,"rotation":0,"scale":1,"position":{"pointX":508.36999797821045,"pointY":375},"width":159,"sublayerTransform":[1,0,0,0,0,1,0,0,0,0,1,0,0,0,0,1],"contentsRect":{"y":0,"x":0,"width":1,"height":1},"opacity":1,"edgeAntialiasingMask":251658240,"height":32,"hidden":false,"anchorPoint":{"pointX":0.5,"pointY":0.5}},"objectID":"3B454D10-C834-4888-914B-9641B0174997","layers":[{"animations":[],"layers":[],"texturedRectangle":{"singleTextureOpacity":1,"textXHeight":0.5625,"textBaseline":0.83749935403466225,"isBackgroundTexture":true,"isVerticalText":false,"textColor":[0.9999966025352478,0.99999994039535522,0.99999994039535522,1],"textureType":6},"initialState":{"affineTransform":[1,0,0,1,0,0],"masksToBounds":false,"rotation":0,"scale":1,"position":{"pointX":82.630002021789551,"pointY":25},"width":159,"sublayerTransform":[1,0,0,0,0,1,0,0,0,0,1,0,0,0,0,1],"contentsRect":{"y":0,"x":0,"width":1,"height":1},"opacity":1,"edgeAntialiasingMask":0,"height":32,"hidden":true,"anchorPoint":{"pointX":0.5,"pointY":0.5}},"texture":"A4964A8E03089811758250A7FBDF6457"}]}]},{"animations":[],"initialState":{"affineTransform":[1,0,0,1,0,0],"masksToBounds":false,"rotation":0,"scale":1,"position":{"pointX":512,"pointY":384},"width":1024,"sublayerTransform":[1,0,0,0,0,1,0,0,0,0,1,0,0,0,0,1],"contentsRect":{"y":0,"x":0,"width":1,"height":1},"opacity":1,"edgeAntialiasingMask":251658240,"height":768,"hidden":false,"anchorPoint":{"pointX":0.5,"pointY":0.5}},"layers":[{"animations":[],"initialState":{"affineTransform":[1,0,0,1,0,0],"masksToBounds":false,"rotation":0,"scale":1,"position":{"pointX":507.95000457763672,"pointY":377.00000011920929},"width":319,"sublayerTransform":[1,0,0,0,0,1,0,0,0,0,1,0,0,0,0,1],"contentsRect":{"y":0,"x":0,"width":1,"height":1},"opacity":1,"edgeAntialiasingMask":251658240,"height":30,"hidden":false,"anchorPoint":{"pointX":0.5,"pointY":0.5}},"objectID":"5F7EC141-10D1-4F1C-AEB2-2787AAFEFDDF","layers":[{"animations":[],"layers":[],"texturedRectangle":{"singleTextureOpacity":1,"textXHeight":0.4366666666666667,"textBaseline":0.74999942978223166,"isBackgroundTexture":true,"isVerticalText":false,"textColor":[0.9999966025352478,0.99999994039535522,0.99999994039535522,1],"textureType":6},"initialState":{"affineTransform":[1,0,0,1,0,0],"masksToBounds":false,"rotation":0,"scale":1,"position":{"pointX":164.04999542236328,"pointY":23.99999988079071},"width":319,"sublayerTransform":[1,0,0,0,0,1,0,0,0,0,1,0,0,0,0,1],"contentsRect":{"y":0,"x":0,"width":1,"height":1},"opacity":1,"edgeAntialiasingMask":0,"height":30,"hidden":true,"anchorPoint":{"pointX":0.5,"pointY":0.5}},"texture":"D381CA1634311E8A93805CE60B7148BA"}]}]},{"animations":[],"initialState":{"affineTransform":[1,0,0,1,0,0],"masksToBounds":false,"rotation":0,"scale":1,"position":{"pointX":512,"pointY":384},"width":1024,"sublayerTransform":[1,0,0,0,0,1,0,0,0,0,1,0,0,0,0,1],"contentsRect":{"y":0,"x":0,"width":1,"height":1},"opacity":1,"edgeAntialiasingMask":251658240,"height":768,"hidden":false,"anchorPoint":{"pointX":0.5,"pointY":0.5}},"layers":[{"animations":[],"initialState":{"affineTransform":[1,0,0,1,0,0],"masksToBounds":false,"rotation":0,"scale":1,"position":{"pointX":505.02499389648438,"pointY":479.13113343715668},"width":752,"sublayerTransform":[1,0,0,0,0,1,0,0,0,0,1,0,0,0,0,1],"contentsRect":{"y":0,"x":0,"width":1,"height":1},"opacity":1,"edgeAntialiasingMask":251658240,"height":64,"hidden":false,"anchorPoint":{"pointX":0.5,"pointY":0.5}},"objectID":"055BCACC-FD79-4887-AB21-D92EBCF3F7BE","layers":[{"animations":[],"layers":[],"texturedRectangle":{"singleTextureOpacity":1,"textXHeight":0.234375,"textBaseline":0.91611119080334902,"isBackgroundTexture":true,"isVerticalText":false,"textColor":[0.9999966025352478,0.99999994039535522,0.99999994039535522,1],"textureType":6},"initialState":{"affineTransform":[1,0,0,1,0,0],"masksToBounds":false,"rotation":0,"scale":1,"position":{"pointX":383.97500610351562,"pointY":40.868866562843323},"width":752,"sublayerTransform":[1,0,0,0,0,1,0,0,0,0,1,0,0,0,0,1],"contentsRect":{"y":0,"x":0,"width":1,"height":1},"opacity":1,"edgeAntialiasingMask":0,"height":64,"hidden":true,"anchorPoint":{"pointX":0.5,"pointY":0.5}},"texture":"6653C94945E0E083797A02191B1D1321"}]}]}]}},{"effects":[{"beginTime":0,"baseLayer":{"animations":[],"initialState":{"affineTransform":[1,0,0,1,0,0],"masksToBounds":false,"rotation":0,"scale":1,"position":{"pointX":508.36999797821045,"pointY":375},"width":159,"sublayerTransform":[1,0,0,0,0,1,0,0,0,0,1,0,0,0,0,1],"contentsRect":{"y":0,"x":0,"width":1,"height":1},"opacity":1,"edgeAntialiasingMask":251658240,"height":32,"hidden":false,"anchorPoint":{"pointX":0.5,"pointY":0.5}},"objectID":"3B454D10-C834-4888-914B-9641B0174997","layers":[{"animations":[{"timeOffset":0,"values":[{"pointX":83.129999999999995,"pointY":25},{"pointX":83.129310165761112,"pointY":24.988378920337851},{"pointX":83.127266244056145,"pointY":24.953946623971696},{"pointX":83.123905237734164,"pointY":24.897326467981749},{"pointX":83.119262419229699,"pointY":24.819112658552619},{"pointX":83.11337144058399,"pointY":24.719872104414826},{"pointX":83.10626443459438,"pointY":24.600146120823975},{"pointX":83.097972107949147,"pointY":24.460451998530026},{"pointX":83.088523827109768,"pointY":24.301284450565007},{"pointX":83.077947697617603,"pointY":24.123116948260115},{"pointX":83.066270637429113,"pointY":23.926402956663516},{"pointX":83.053518444818593,"pointY":23.711577078443284},{"pointX":83.039715861331132,"pointY":23.479056114404806},{"pointX":83.024886630218361,"pointY":23.229240047910963},{"pointX":83.00905355074562,"pointY":22.962512959750846},{"pointX":82.992238528720137,"pointY":22.679243879346537},{"pointX":82.974462623555112,"pointY":22.379787577605438},{"pointX":82.955746092154484,"pointY":22.064485306209438},{"pointX":82.936108429875119,"pointY":21.733665487672567},{"pointX":82.915568408799416,"pointY":21.387644360089272},{"pointX":82.894144113529578,"pointY":21.026726580130322},{"pointX":82.871852974694988,"pointY":20.651205787516158},{"pointX":82.848711800347431,"pointY":20.261365133904924},{"pointX":82.824736805402537,"pointY":19.857477778869686},{"pointX":82.79994363927247,"pointY":19.439807355403509},{"pointX":82.774347411821765,"pointY":19.008608407178293},{"pointX":82.747962717767564,"pointY":18.564126799592295},{"pointX":82.720803659634015,"pointY":18.106600106467891},{"pointX":82.692883869362859,"pointY":17.63625797410543},{"pointX":82.664216528672526,"pointY":17.153322464257357},{"pointX":82.634814388251201,"pointY":16.658008377458316},{"pointX":82.604689785862234,"pointY":16.150523558031367},{"pointX":82.573854663433707,"pointY":15.631069181983696},{"pointX":82.54232058319883,"pointY":15.099840028909515},{"pointX":82.510098742948045,"pointY":14.557024738930364},{"pointX":82.477199990449293,"pointY":14.002806055621759},{"pointX":82.443634837088482,"pointY":13.437361055803786},{"pointX":82.409413470778333,"pointY":12.860861367004297},{"pointX":82.374545768179757,"pointY":12.273473373343712},{"pointX":82.339041306276997,"pointY":11.675358410533011},{"pointX":82.302909373344775,"pointY":11.06667295062552},{"pointX":82.266158979342009,"pointY":10.447568777114805},{"pointX":82.228798865765441,"pointY":9.8181931509282609},{"pointX":82.190837514992708,"pointY":9.1786889678237955},{"pointX":82.15228315914328,"pointY":8.5291949076619886},{"pointX":82.113143788482859,"pointY":7.8698455759886965},{"pointX":82.073427159395422,"pointY":7.2007716383336433},{"pointX":82.033140801945123,"pointY":6.5220999475987806},{"pointX":81.99229202704845,"pointY":5.8339536648831842},{"pointX":81.950887933275922,"pointY":5.1364523740651835},{"pointX":81.908935413300824,"pointY":4.4297121904382317},{"pointX":81.866441160011107,"pointY":3.7138458636739915},{"pointX":81.823411672299486,"pointY":2.9889628753643529},{"pointX":81.779853260545792,"pointY":2.2551695313748938},{"pointX":81.735772051803465,"pointY":1.5125690492216308},{"pointX":81.691173994702567,"pointY":0.76126164066527335},{"pointX":81.646064864079165,"pointY":0.0013445897000376877},{"pointX":81.600450265340882,"pointY":-0.76708767390406485},{"pointX":81.554335638576987,"pointY":-1.5439435053617412},{"pointX":81.507726262420618,"pointY":-2.329133979808625},{"pointX":81.460627257669756,"pointY":-3.1225728313014467},{"pointX":81.413043590672686,"pointY":-3.9241763957863056},{"pointX":81.364980076482638,"pointY":-4.7338635579542014},{"pointX":81.316441381785665,"pointY":-5.5515557019187858},{"pointX":81.267432027604428,"pointY":-6.3771766656665854},{"pointX":81.217956391780049,"pointY":-7.2106526992476354},{"pointX":81.168018711233046,"pointY":-8.0519124266882276},{"pointX":81.117623084003043,"pointY":-8.900886811627986},{"pointX":81.066773471066426,"pointY":-9.7575091267002101},{"pointX":81.015473697929508,"pointY":-10.621714926693445},{"pointX":80.963727455993563,"pointY":-11.493442025554492},{"pointX":80.91153830368718,"pointY":-12.372630477314885},{"pointX":80.858909667359086,"pointY":-13.259222561047643},{"pointX":80.805844841924028,"pointY":-14.153162769987699},{"pointX":80.797062522717084,"pointY":-15.055571070591693},{"pointX":80.803382122095115,"pointY":-15.965627083081738},{"pointX":80.809751770581329,"pointY":-16.882890434060794},{"pointX":80.816171143533765,"pointY":-17.807314373352529},{"pointX":80.82263993181752,"pointY":-18.738854383885034},{"pointX":80.829157841936222,"pointY":-19.677468200609226},{"pointX":80.835724596206305,"pointY":-20.623115835620148},{"pointX":80.842339932978362,"pointY":-21.575759610000446},{"pointX":80.849003606908965,"pointY":-22.535364192992752},{"pointX":80.855715389288619,"pointY":-23.501896649206291},{"pointX":80.862475068430982,"pointY":-24.47532649468214},{"pointX":80.869282450130498,"pointY":-25.45562576277991},{"pointX":80.876137358195848,"pointY":-26.442769081014326},{"pointX":80.883039635068855,"pointY":-27.436733760166945},{"pointX":80.889989142539335,"pointY":-28.437499897235504},{"pointX":80.89698576256896,"pointY":-29.445050494068113},{"pointX":80.904029398239189,"pointY":-30.459371593878164},{"pointX":80.911119974841611,"pointY":-31.480452438258745},{"pointX":80.918257441132511,"pointY":-32.508285647838143},{"pointX":80.925441770777752,"pointY":-33.542867430364687},{"pointX":80.93267296402027,"pointY":-34.584197820818567},{"pointX":80.939951049608737,"pointY":-35.632280959162905},{"pointX":80.947276087035661,"pointY":-36.687125412639361},{"pointX":80.954648169144292,"pointY":-37.748744551166951},{"pointX":80.962067425178446,"pointY":-38.817156986543097},{"pointX":80.969534024369167,"pointY":-39.892387088945078},{"pointX":80.977048180177732,"pointY":-40.974465597933587},{"pointX":80.984610155348705,"pointY":-42.063430350125714},{"pointX":80.992220267973948,"pointY":-43.159327152445826},{"pointX":80.999878898832947,"pointY":-44.262210839173491},{"pointX":81.007586500365591,"pointY":-45.37214656406411},{"pointX":81.015343607763029,"pointY":-46.489211397496312},{"pointX":81.023150852851899,"pointY":-47.613496325876028},{"pointX":81.031008981730395,"pointY":-48.745108791322153},{"pointX":81.038918877549946,"pointY":-49.884175972347897},{"pointX":81.046881590526226,"pointY":-51.030849105618515},{"pointX":81.054898378397567,"pointY":-52.185309312152853},{"pointX":81.062970762491801,"pointY":-53.347775671276793},{"pointX":81.071100608069855,"pointY":-54.518516790507007},{"pointX":81.079290244338466,"pointY":-55.697868088041389},{"pointX":81.087542653461554,"pointY":-56.886259011380147},{"pointX":81.095861789802001,"pointY":-58.084259009874728},{"pointX":81.10425317422542,"pointY":-59.292663117610687},{"pointX":81.112725175096756,"pointY":-60.512676423770216},{"pointX":81.121292573400154,"pointY":-61.74642746889333},{"pointX":81.129997656062301,"pointY":-63.000005795940453}],"beginTime":1e-100,"repeatCount":0,"fillMode":"both","property":"position","autoreverses":false,"duration":1,"keyTimes":[0,0.0084033613445378148,0.01680672268907563,0.025210084033613446,0.033613445378151259,0.042016806722689079,0.050420168067226892,0.058823529411764705,0.067226890756302518,0.075630252100840331,0.084033613445378158,0.092436974789915971,0.10084033613445378,0.1092436974789916,0.11764705882352941,0.12605042016806722,0.13445378151260504,0.14285714285714285,0.15126050420168066,0.15966386554621848,0.16806722689075632,0.17647058823529413,0.18487394957983194,0.19327731092436976,0.20168067226890757,0.21008403361344538,0.21848739495798319,0.22689075630252101,0.23529411764705882,0.24369747899159663,0.25210084033613445,0.26050420168067229,0.26890756302521007,0.27731092436974791,0.2857142857142857,0.29411764705882354,0.30252100840336132,0.31092436974789917,0.31932773109243695,0.32773109243697479,0.33613445378151263,0.34453781512605042,0.35294117647058826,0.36134453781512604,0.36974789915966388,0.37815126050420167,0.38655462184873951,0.3949579831932773,0.40336134453781514,0.41176470588235292,0.42016806722689076,0.42857142857142855,0.43697478991596639,0.44537815126050423,0.45378151260504201,0.46218487394957986,0.47058823529411764,0.47899159663865548,0.48739495798319327,0.49579831932773111,0.50420168067226889,0.51260504201680668,0.52100840336134457,0.52941176470588236,0.53781512605042014,0.54621848739495793,0.55462184873949583,0.56302521008403361,0.5714285714285714,0.57983193277310929,0.58823529411764708,0.59663865546218486,0.60504201680672265,0.61344537815126055,0.62184873949579833,0.63025210084033612,0.6386554621848739,0.6470588235294118,0.65546218487394958,0.66386554621848737,0.67226890756302526,0.68067226890756305,0.68907563025210083,0.69747899159663862,0.70588235294117652,0.7142857142857143,0.72268907563025209,0.73109243697478987,0.73949579831932777,0.74789915966386555,0.75630252100840334,0.76470588235294112,0.77310924369747902,0.78151260504201681,0.78991596638655459,0.79831932773109249,0.80672268907563027,0.81512605042016806,0.82352941176470584,0.83193277310924374,0.84033613445378152,0.84873949579831931,0.8571428571428571,0.86554621848739499,0.87394957983193278,0.88235294117647056,0.89075630252100846,0.89915966386554624,0.90756302521008403,0.91596638655462181,0.92436974789915971,0.9327731092436975,0.94117647058823528,0.94957983193277307,0.95798319327731096,0.96638655462184875,0.97478991596638653,0.98319327731092432,0.99159663865546221,1]}],"layers":[],"texturedRectangle":{"singleTextureOpacity":1,"textXHeight":0.5625,"textBaseline":0.83749935403466225,"isBackgroundTexture":true,"isVerticalText":false,"textColor":[0.9999966025352478,0.99999994039535522,0.99999994039535522,1],"textureType":6},"initialState":{"affineTransform":[1,0,0,1,0,0],"masksToBounds":false,"rotation":0,"scale":1,"position":{"pointX":83.129999999999995,"pointY":25},"width":159,"sublayerTransform":[1,0,0,0,0,1,0,0,0,0,1,0,0,0,0,1],"contentsRect":{"y":0,"x":0,"width":1,"height":1},"opacity":1,"edgeAntialiasingMask":0,"height":32,"hidden":false,"anchorPoint":{"pointX":0.50314464137239279,"pointY":0.5}},"texture":"A4964A8E03089811758250A7FBDF6457"}]},"effects":[],"duration":1,"type":"actionBuild","attributes":{"direction":0},"name":"apple:action-motion-path","objectID":"3B454D10-C834-4888-914B-9641B0174997"},{"beginTime":0,"baseLayer":{"animations":[],"initialState":{"affineTransform":[1,0,0,1,0,0],"masksToBounds":false,"rotation":0,"scale":1,"position":{"pointX":507.95000457763672,"pointY":377.00000011920929},"width":319,"sublayerTransform":[1,0,0,0,0,1,0,0,0,0,1,0,0,0,0,1],"contentsRect":{"y":0,"x":0,"width":1,"height":1},"opacity":1,"edgeAntialiasingMask":251658240,"height":30,"hidden":false,"anchorPoint":{"pointX":0.5,"pointY":0.5}},"objectID":"5F7EC141-10D1-4F1C-AEB2-2787AAFEFDDF","layers":[{"animations":[],"initialState":{"affineTransform":[1,0,0,1,0,0],"masksToBounds":false,"rotation":0,"scale":1,"position":{"pointX":163.54999542236328,"pointY":21.99999988079071},"width":319,"sublayerTransform":[1,0,0,0,0,1,0,0,0,0,1,-0.00049229876906403734,0,0,0,1],"contentsRect":{"y":0,"x":0,"width":1,"height":1},"opacity":1,"edgeAntialiasingMask":251658240,"height":30,"hidden":false,"anchorPoint":{"pointX":0.5126959104149319,"pointY":0.73333332935969031}},"layers":[{"animations":[{"timeOffset":0,"beginTime":1e-100,"repeatCount":0,"animations":[{"timeOffset":0,"from":{"scalar":0},"beginTime":0,"repeatCount":0,"fillMode":"both","duration":1,"autoreverses":false,"timingFunction":"EaseInEaseOut","property":"opacity","to":{"scalar":1}},{"timeOffset":0,"from":{"scalar":false},"beginTime":0,"repeatCount":0,"fillMode":"forwards","property":"hidden","autoreverses":false,"duration":1,"to":{"scalar":false}}],"fillMode":"both","autoreverses":false,"duration":1}],"layers":[],"texturedRectangle":{"singleTextureOpacity":1,"textXHeight":0.4366666666666667,"textBaseline":0.74999942978223166,"isBackgroundTexture":true,"isVerticalText":false,"textColor":[0.9999966025352478,0.99999994039535522,0.99999994039535522,1],"textureType":6},"initialState":{"affineTransform":[1,0,0,1,0,0],"masksToBounds":false,"rotation":0,"scale":1,"position":{"pointX":164.04999542236328,"pointY":23.99999988079071},"width":319,"sublayerTransform":[1,0,0,0,0,1,0,0,0,0,1,0,0,0,0,1],"contentsRect":{"y":0,"x":0,"width":1,"height":1},"opacity":1,"edgeAntialiasingMask":0,"height":30,"hidden":true,"anchorPoint":{"pointX":0.5,"pointY":0.5}},"texture":"D381CA1634311E8A93805CE60B7148BA"}]}]},"effects":[],"duration":1,"type":"buildIn","attributes":{"direction":0},"name":"apple:dissolve character","objectID":"5F7EC141-10D1-4F1C-AEB2-2787AAFEFDDF"}],"automaticPlay":false,"hyperlinks":[],"accessibility":[{"text":"什麼是UX ?","targetRectangle":{"y":363,"x":433.36999797821045,"width":157.25999999999999,"height":42}}],"baseLayer":{"animations":[],"initialState":{"affineTransform":[1,0,0,1,0,0],"masksToBounds":false,"rotation":0,"scale":1,"position":{"pointX":512,"pointY":384},"width":1024,"sublayerTransform":[1,0,0,0,0,1,0,0,0,0,1,0,0,0,0,1],"contentsRect":{"y":0,"x":0,"width":1,"height":1},"opacity":1,"edgeAntialiasingMask":251658240,"height":768,"hidden":false,"anchorPoint":{"pointX":0.5,"pointY":0.5}},"layers":[{"animations":[],"initialState":{"affineTransform":[1,0,0,1,0,0],"masksToBounds":false,"rotation":0,"scale":1,"position":{"pointX":512,"pointY":384},"width":1024,"sublayerTransform":[1,0,0,0,0,1,0,0,0,0,1,0,0,0,0,1],"contentsRect":{"y":0,"x":0,"width":1,"height":1},"opacity":1,"edgeAntialiasingMask":251658240,"height":768,"hidden":false,"anchorPoint":{"pointX":0.5,"pointY":0.5}},"layers":[{"animations":[],"initialState":{"affineTransform":[1,0,0,1,0,0],"masksToBounds":false,"rotation":0,"scale":1,"position":{"pointX":512,"pointY":384},"width":1024,"sublayerTransform":[1,0,0,0,0,1,0,0,0,0,1,0,0,0,0,1],"contentsRect":{"y":0,"x":0,"width":1,"height":1},"opacity":1,"edgeAntialiasingMask":251658240,"height":768,"hidden":false,"anchorPoint":{"pointX":0.5,"pointY":0.5}},"layers":[{"animations":[],"layers":[],"texturedRectangle":{"isBackgroundTexture":true,"singleTextureOpacity":1,"textureType":1,"textBaseline":0,"textXHeight":0,"isVerticalText":false},"initialState":{"affineTransform":[1,0,0,1,0,0],"masksToBounds":false,"rotation":0,"scale":1,"position":{"pointX":512,"pointY":384},"width":1024,"sublayerTransform":[1,0,0,0,0,1,0,0,0,0,1,0,0,0,0,1],"contentsRect":{"y":0,"x":0,"width":1,"height":1},"opacity":1,"edgeAntialiasingMask":0,"height":768,"hidden":false,"anchorPoint":{"pointX":0.5,"pointY":0.5}},"texture":"DB8451458D98EFA7506DBEBC2B1323F0"}]}]},{"animations":[],"initialState":{"affineTransform":[1,0,0,1,0,0],"masksToBounds":false,"rotation":0,"scale":1,"position":{"pointX":512,"pointY":384},"width":1024,"sublayerTransform":[1,0,0,0,0,1,0,0,0,0,1,0,0,0,0,1],"contentsRect":{"y":0,"x":0,"width":1,"height":1},"opacity":1,"edgeAntialiasingMask":251658240,"height":768,"hidden":false,"anchorPoint":{"pointX":0.5,"pointY":0.5}},"layers":[{"animations":[],"initialState":{"affineTransform":[1,0,0,1,0,0],"masksToBounds":false,"rotation":0,"scale":1,"position":{"pointX":508.36999797821045,"pointY":375},"width":159,"sublayerTransform":[1,0,0,0,0,1,0,0,0,0,1,0,0,0,0,1],"contentsRect":{"y":0,"x":0,"width":1,"height":1},"opacity":1,"edgeAntialiasingMask":251658240,"height":32,"hidden":false,"anchorPoint":{"pointX":0.5,"pointY":0.5}},"objectID":"3B454D10-C834-4888-914B-9641B0174997","layers":[{"animations":[],"layers":[],"texturedRectangle":{"singleTextureOpacity":1,"textXHeight":0.5625,"textBaseline":0.83749935403466225,"isBackgroundTexture":true,"isVerticalText":false,"textColor":[0.9999966025352478,0.99999994039535522,0.99999994039535522,1],"textureType":6},"initialState":{"affineTransform":[1,0,0,1,0,0],"masksToBounds":false,"rotation":0,"scale":1,"position":{"pointX":83.129999999999995,"pointY":25},"width":159,"sublayerTransform":[1,0,0,0,0,1,0,0,0,0,1,0,0,0,0,1],"contentsRect":{"y":0,"x":0,"width":1,"height":1},"opacity":1,"edgeAntialiasingMask":0,"height":32,"hidden":false,"anchorPoint":{"pointX":0.50314464137239279,"pointY":0.5}},"texture":"A4964A8E03089811758250A7FBDF6457"}]}]},{"animations":[],"initialState":{"affineTransform":[1,0,0,1,0,0],"masksToBounds":false,"rotation":0,"scale":1,"position":{"pointX":512,"pointY":384},"width":1024,"sublayerTransform":[1,0,0,0,0,1,0,0,0,0,1,0,0,0,0,1],"contentsRect":{"y":0,"x":0,"width":1,"height":1},"opacity":1,"edgeAntialiasingMask":251658240,"height":768,"hidden":false,"anchorPoint":{"pointX":0.5,"pointY":0.5}},"layers":[{"animations":[],"initialState":{"affineTransform":[1,0,0,1,0,0],"masksToBounds":false,"rotation":0,"scale":1,"position":{"pointX":507.95000457763672,"pointY":377.00000011920929},"width":319,"sublayerTransform":[1,0,0,0,0,1,0,0,0,0,1,0,0,0,0,1],"contentsRect":{"y":0,"x":0,"width":1,"height":1},"opacity":1,"edgeAntialiasingMask":251658240,"height":30,"hidden":false,"anchorPoint":{"pointX":0.5,"pointY":0.5}},"objectID":"5F7EC141-10D1-4F1C-AEB2-2787AAFEFDDF","layers":[{"animations":[],"layers":[],"texturedRectangle":{"singleTextureOpacity":1,"textXHeight":0.4366666666666667,"textBaseline":0.74999942978223166,"isBackgroundTexture":true,"isVerticalText":false,"textColor":[0.9999966025352478,0.99999994039535522,0.99999994039535522,1],"textureType":6},"initialState":{"affineTransform":[1,0,0,1,0,0],"masksToBounds":false,"rotation":0,"scale":1,"position":{"pointX":164.04999542236328,"pointY":23.99999988079071},"width":319,"sublayerTransform":[1,0,0,0,0,1,0,0,0,0,1,0,0,0,0,1],"contentsRect":{"y":0,"x":0,"width":1,"height":1},"opacity":1,"edgeAntialiasingMask":0,"height":30,"hidden":true,"anchorPoint":{"pointX":0.5,"pointY":0.5}},"texture":"D381CA1634311E8A93805CE60B7148BA"}]}]},{"animations":[],"initialState":{"affineTransform":[1,0,0,1,0,0],"masksToBounds":false,"rotation":0,"scale":1,"position":{"pointX":512,"pointY":384},"width":1024,"sublayerTransform":[1,0,0,0,0,1,0,0,0,0,1,0,0,0,0,1],"contentsRect":{"y":0,"x":0,"width":1,"height":1},"opacity":1,"edgeAntialiasingMask":251658240,"height":768,"hidden":false,"anchorPoint":{"pointX":0.5,"pointY":0.5}},"layers":[{"animations":[],"initialState":{"affineTransform":[1,0,0,1,0,0],"masksToBounds":false,"rotation":0,"scale":1,"position":{"pointX":505.02499389648438,"pointY":479.13113343715668},"width":752,"sublayerTransform":[1,0,0,0,0,1,0,0,0,0,1,0,0,0,0,1],"contentsRect":{"y":0,"x":0,"width":1,"height":1},"opacity":1,"edgeAntialiasingMask":251658240,"height":64,"hidden":false,"anchorPoint":{"pointX":0.5,"pointY":0.5}},"objectID":"055BCACC-FD79-4887-AB21-D92EBCF3F7BE","layers":[{"animations":[],"layers":[],"texturedRectangle":{"singleTextureOpacity":1,"textXHeight":0.234375,"textBaseline":0.91611119080334902,"isBackgroundTexture":true,"isVerticalText":false,"textColor":[0.9999966025352478,0.99999994039535522,0.99999994039535522,1],"textureType":6},"initialState":{"affineTransform":[1,0,0,1,0,0],"masksToBounds":false,"rotation":0,"scale":1,"position":{"pointX":383.97500610351562,"pointY":40.868866562843323},"width":752,"sublayerTransform":[1,0,0,0,0,1,0,0,0,0,1,0,0,0,0,1],"contentsRect":{"y":0,"x":0,"width":1,"height":1},"opacity":1,"edgeAntialiasingMask":0,"height":64,"hidden":true,"anchorPoint":{"pointX":0.5,"pointY":0.5}},"texture":"6653C94945E0E083797A02191B1D1321"}]}]}]}},{"effects":[{"beginTime":0,"baseLayer":{"animations":[],"initialState":{"affineTransform":[1,0,0,1,0,0],"masksToBounds":false,"rotation":0,"scale":1,"position":{"pointX":505.02499389648438,"pointY":479.13113343715668},"width":752,"sublayerTransform":[1,0,0,0,0,1,0,0,0,0,1,0,0,0,0,1],"contentsRect":{"y":0,"x":0,"width":1,"height":1},"opacity":1,"edgeAntialiasingMask":251658240,"height":64,"hidden":false,"anchorPoint":{"pointX":0.5,"pointY":0.5}},"objectID":"055BCACC-FD79-4887-AB21-D92EBCF3F7BE","layers":[{"animations":[],"initialState":{"affineTransform":[1,0,0,1,0,0],"masksToBounds":false,"rotation":0,"scale":1,"position":{"pointX":382.97500610351562,"pointY":-63.131133437156677},"width":752,"sublayerTransform":[1,0,0,0,0,1,0,0,0,0,1,-0.00049229876906403734,0,0,0,1],"contentsRect":{"y":0,"x":0,"width":1,"height":1},"opacity":1,"edgeAntialiasingMask":251658240,"height":64,"hidden":false,"anchorPoint":{"pointX":0.509275274073824,"pointY":-0.98642395995557308}},"layers":[{"animations":[{"timeOffset":0,"beginTime":1e-100,"repeatCount":0,"animations":[{"timeOffset":0,"from":{"scalar":0},"beginTime":0,"repeatCount":0,"fillMode":"both","duration":1,"autoreverses":false,"timingFunction":"EaseInEaseOut","property":"opacity","to":{"scalar":1}},{"timeOffset":0,"from":{"scalar":false},"beginTime":0,"repeatCount":0,"fillMode":"forwards","property":"hidden","autoreverses":false,"duration":1,"to":{"scalar":false}}],"fillMode":"both","autoreverses":false,"duration":1}],"layers":[],"texturedRectangle":{"singleTextureOpacity":1,"textXHeight":0.234375,"textBaseline":0.91611119080334902,"isBackgroundTexture":true,"isVerticalText":false,"textColor":[0.9999966025352478,0.99999994039535522,0.99999994039535522,1],"textureType":6},"initialState":{"affineTransform":[1,0,0,1,0,0],"masksToBounds":false,"rotation":0,"scale":1,"position":{"pointX":383.97500610351562,"pointY":40.868866562843323},"width":752,"sublayerTransform":[1,0,0,0,0,1,0,0,0,0,1,0,0,0,0,1],"contentsRect":{"y":0,"x":0,"width":1,"height":1},"opacity":1,"edgeAntialiasingMask":0,"height":64,"hidden":true,"anchorPoint":{"pointX":0.5,"pointY":0.5}},"texture":"6653C94945E0E083797A02191B1D1321"}]}]},"effects":[],"duration":1,"type":"buildIn","attributes":{"direction":0},"name":"apple:dissolve character","objectID":"055BCACC-FD79-4887-AB21-D92EBCF3F7BE"}],"automaticPlay":false,"hyperlinks":[],"accessibility":[{"text":"什麼是UX ?","targetRectangle":{"y":363,"x":433.36999797821045,"width":157.25999999999999,"height":42}},{"text":"User Experience 使用者經驗","targetRectangle":{"y":366.00000011920929,"x":352.95000457763672,"width":318.10000000000002,"height":36}}],"baseLayer":{"animations":[],"initialState":{"affineTransform":[1,0,0,1,0,0],"masksToBounds":false,"rotation":0,"scale":1,"position":{"pointX":512,"pointY":384},"width":1024,"sublayerTransform":[1,0,0,0,0,1,0,0,0,0,1,0,0,0,0,1],"contentsRect":{"y":0,"x":0,"width":1,"height":1},"opacity":1,"edgeAntialiasingMask":251658240,"height":768,"hidden":false,"anchorPoint":{"pointX":0.5,"pointY":0.5}},"layers":[{"animations":[],"initialState":{"affineTransform":[1,0,0,1,0,0],"masksToBounds":false,"rotation":0,"scale":1,"position":{"pointX":512,"pointY":384},"width":1024,"sublayerTransform":[1,0,0,0,0,1,0,0,0,0,1,0,0,0,0,1],"contentsRect":{"y":0,"x":0,"width":1,"height":1},"opacity":1,"edgeAntialiasingMask":251658240,"height":768,"hidden":false,"anchorPoint":{"pointX":0.5,"pointY":0.5}},"layers":[{"animations":[],"initialState":{"affineTransform":[1,0,0,1,0,0],"masksToBounds":false,"rotation":0,"scale":1,"position":{"pointX":512,"pointY":384},"width":1024,"sublayerTransform":[1,0,0,0,0,1,0,0,0,0,1,0,0,0,0,1],"contentsRect":{"y":0,"x":0,"width":1,"height":1},"opacity":1,"edgeAntialiasingMask":251658240,"height":768,"hidden":false,"anchorPoint":{"pointX":0.5,"pointY":0.5}},"layers":[{"animations":[],"layers":[],"texturedRectangle":{"isBackgroundTexture":true,"singleTextureOpacity":1,"textureType":1,"textBaseline":0,"textXHeight":0,"isVerticalText":false},"initialState":{"affineTransform":[1,0,0,1,0,0],"masksToBounds":false,"rotation":0,"scale":1,"position":{"pointX":512,"pointY":384},"width":1024,"sublayerTransform":[1,0,0,0,0,1,0,0,0,0,1,0,0,0,0,1],"contentsRect":{"y":0,"x":0,"width":1,"height":1},"opacity":1,"edgeAntialiasingMask":0,"height":768,"hidden":false,"anchorPoint":{"pointX":0.5,"pointY":0.5}},"texture":"DB8451458D98EFA7506DBEBC2B1323F0"}]}]},{"animations":[],"initialState":{"affineTransform":[1,0,0,1,0,0],"masksToBounds":false,"rotation":0,"scale":1,"position":{"pointX":512,"pointY":384},"width":1024,"sublayerTransform":[1,0,0,0,0,1,0,0,0,0,1,0,0,0,0,1],"contentsRect":{"y":0,"x":0,"width":1,"height":1},"opacity":1,"edgeAntialiasingMask":251658240,"height":768,"hidden":false,"anchorPoint":{"pointX":0.5,"pointY":0.5}},"layers":[{"animations":[],"initialState":{"affineTransform":[1,0,0,1,0,0],"masksToBounds":false,"rotation":0,"scale":1,"position":{"pointX":506.36999559402466,"pointY":287},"width":159,"sublayerTransform":[1,0,0,0,0,1,0,0,0,0,1,0,0,0,0,1],"contentsRect":{"y":0,"x":0,"width":1,"height":1},"opacity":1,"edgeAntialiasingMask":251658240,"height":32,"hidden":false,"anchorPoint":{"pointX":0.5,"pointY":0.5}},"objectID":"3B454D10-C834-4888-914B-9641B0174997","layers":[{"animations":[],"layers":[],"texturedRectangle":{"singleTextureOpacity":1,"textXHeight":0.5625,"textBaseline":0.83749935403466225,"isBackgroundTexture":true,"isVerticalText":false,"textColor":[0.9999966025352478,0.99999994039535522,0.99999994039535522,1],"textureType":6},"initialState":{"affineTransform":[1,0,0,1,0,0],"masksToBounds":false,"rotation":0,"scale":1,"position":{"pointX":83.129999999999995,"pointY":25},"width":159,"sublayerTransform":[1,0,0,0,0,1,0,0,0,0,1,0,0,0,0,1],"contentsRect":{"y":0,"x":0,"width":1,"height":1},"opacity":1,"edgeAntialiasingMask":0,"height":32,"hidden":false,"anchorPoint":{"pointX":0.50314464137239279,"pointY":0.5}},"texture":"A4964A8E03089811758250A7FBDF6457"}]}]},{"animations":[],"initialState":{"affineTransform":[1,0,0,1,0,0],"masksToBounds":false,"rotation":0,"scale":1,"position":{"pointX":512,"pointY":384},"width":1024,"sublayerTransform":[1,0,0,0,0,1,0,0,0,0,1,0,0,0,0,1],"contentsRect":{"y":0,"x":0,"width":1,"height":1},"opacity":1,"edgeAntialiasingMask":251658240,"height":768,"hidden":false,"anchorPoint":{"pointX":0.5,"pointY":0.5}},"layers":[{"animations":[],"initialState":{"affineTransform":[1,0,0,1,0,0],"masksToBounds":false,"rotation":0,"scale":1,"position":{"pointX":507.95000457763672,"pointY":377.00000011920929},"width":319,"sublayerTransform":[1,0,0,0,0,1,0,0,0,0,1,0,0,0,0,1],"contentsRect":{"y":0,"x":0,"width":1,"height":1},"opacity":1,"edgeAntialiasingMask":251658240,"height":30,"hidden":false,"anchorPoint":{"pointX":0.5,"pointY":0.5}},"objectID":"5F7EC141-10D1-4F1C-AEB2-2787AAFEFDDF","layers":[{"animations":[],"layers":[],"texturedRectangle":{"singleTextureOpacity":1,"textXHeight":0.4366666666666667,"textBaseline":0.74999942978223166,"isBackgroundTexture":true,"isVerticalText":false,"textColor":[0.9999966025352478,0.99999994039535522,0.99999994039535522,1],"textureType":6},"initialState":{"affineTransform":[1,0,0,1,0,0],"masksToBounds":false,"rotation":0,"scale":1,"position":{"pointX":164.04999542236328,"pointY":23.99999988079071},"width":319,"sublayerTransform":[1,0,0,0,0,1,0,0,0,0,1,0,0,0,0,1],"contentsRect":{"y":0,"x":0,"width":1,"height":1},"opacity":1,"edgeAntialiasingMask":0,"height":30,"hidden":false,"anchorPoint":{"pointX":0.5,"pointY":0.5}},"texture":"D381CA1634311E8A93805CE60B7148BA"}]}]},{"animations":[],"initialState":{"affineTransform":[1,0,0,1,0,0],"masksToBounds":false,"rotation":0,"scale":1,"position":{"pointX":512,"pointY":384},"width":1024,"sublayerTransform":[1,0,0,0,0,1,0,0,0,0,1,0,0,0,0,1],"contentsRect":{"y":0,"x":0,"width":1,"height":1},"opacity":1,"edgeAntialiasingMask":251658240,"height":768,"hidden":false,"anchorPoint":{"pointX":0.5,"pointY":0.5}},"layers":[{"animations":[],"initialState":{"affineTransform":[1,0,0,1,0,0],"masksToBounds":false,"rotation":0,"scale":1,"position":{"pointX":505.02499389648438,"pointY":479.13113343715668},"width":752,"sublayerTransform":[1,0,0,0,0,1,0,0,0,0,1,0,0,0,0,1],"contentsRect":{"y":0,"x":0,"width":1,"height":1},"opacity":1,"edgeAntialiasingMask":251658240,"height":64,"hidden":false,"anchorPoint":{"pointX":0.5,"pointY":0.5}},"objectID":"055BCACC-FD79-4887-AB21-D92EBCF3F7BE","layers":[{"animations":[],"layers":[],"texturedRectangle":{"singleTextureOpacity":1,"textXHeight":0.234375,"textBaseline":0.91611119080334902,"isBackgroundTexture":true,"isVerticalText":false,"textColor":[0.9999966025352478,0.99999994039535522,0.99999994039535522,1],"textureType":6},"initialState":{"affineTransform":[1,0,0,1,0,0],"masksToBounds":false,"rotation":0,"scale":1,"position":{"pointX":383.97500610351562,"pointY":40.868866562843323},"width":752,"sublayerTransform":[1,0,0,0,0,1,0,0,0,0,1,0,0,0,0,1],"contentsRect":{"y":0,"x":0,"width":1,"height":1},"opacity":1,"edgeAntialiasingMask":0,"height":64,"hidden":true,"anchorPoint":{"pointX":0.5,"pointY":0.5}},"texture":"6653C94945E0E083797A02191B1D1321"}]}]}]}},{"effects":[{"beginTime":0,"baseLayer":{"animations":[],"initialState":{"affineTransform":[1,0,0,1,0,0],"masksToBounds":false,"rotation":0,"scale":1,"position":{"pointX":512,"pointY":384},"width":1024,"sublayerTransform":[1,0,0,0,0,1,0,0,0,0,1,0,0,0,0,1],"contentsRect":{"y":0,"x":0,"width":1,"height":1},"opacity":1,"edgeAntialiasingMask":251658240,"height":768,"hidden":false,"anchorPoint":{"pointX":0.5,"pointY":0.5}},"objectID":"0","layers":[{"animations":[],"initialState":{"affineTransform":[1,0,0,1,0,0],"masksToBounds":false,"rotation":0,"scale":1,"position":{"pointX":512,"pointY":384},"width":1024,"sublayerTransform":[1,0,0,0,0,1,0,0,0,0,1,-0.00049229876906403734,0,0,0,1],"contentsRect":{"y":0,"x":0,"width":1,"height":1},"opacity":1,"edgeAntialiasingMask":251658240,"height":768,"hidden":false,"anchorPoint":{"pointX":0.5,"pointY":0.5}},"layers":[{"animations":[],"layers":[],"texturedRectangle":{"isBackgroundTexture":false,"singleTextureOpacity":1,"textureType":0,"textBaseline":0,"textXHeight":0,"isVerticalText":false},"initialState":{"affineTransform":[1,0,0,1,0,0],"masksToBounds":false,"rotation":0,"scale":1,"position":{"pointX":512,"pointY":384},"width":1024,"sublayerTransform":[1,0,0,0,0,1,0,0,0,0,1,0,0,0,0,1],"contentsRect":{"y":0,"x":0,"width":1,"height":1},"opacity":1,"edgeAntialiasingMask":0,"height":768,"hidden":false,"anchorPoint":{"pointX":0.5,"pointY":0.5}},"texture":"DB8451458D98EFA7506DBEBC2B1323F0"},{"animations":[{"timeOffset":0,"from":{"scalar":false},"beginTime":0,"repeatCount":0,"fillMode":"both","property":"hidden","autoreverses":false,"duration":0.01,"to":{"scalar":true}}],"layers":[],"texturedRectangle":{"isBackgroundTexture":false,"singleTextureOpacity":1,"textureType":0,"textBaseline":0,"textXHeight":0,"isVerticalText":false},"initialState":{"affineTransform":[1,0,0,1,0,0],"masksToBounds":false,"rotation":0,"scale":1,"position":{"pointX":512,"pointY":384},"width":1024,"sublayerTransform":[1,0,0,0,0,1,0,0,0,0,1,0,0,0,0,1],"contentsRect":{"y":0,"x":0,"width":1,"height":1},"opacity":1,"edgeAntialiasingMask":0,"height":768,"hidden":false,"anchorPoint":{"pointX":0.5,"pointY":0.5}},"texture":"085A49673D7C8714419088366BDA5601"}]}]},"effects":[],"duration":0.01,"type":"transition","attributes":{"direction":0},"name":"none","objectID":"0"}],"automaticPlay":false,"hyperlinks":[],"accessibility":[{"text":"什麼是UX ?","targetRectangle":{"y":363,"x":433.36999797821045,"width":157.25999999999999,"height":42}},{"text":"透過數據，推回去觀察使用者的行為與感覺，並從中找出解決問題。","targetRectangle":{"y":451.13113343715668,"x":136.99999389648437,"width":750,"height":36}},{"text":"這裡的數據  是根據 USER在使用產品時所產生的行為。","targetRectangle":{"y":487.13113343715668,"x":206.4374938964844,"width":611.125,"height":36}},{"text":"User Experience 使用者經驗","targetRectangle":{"y":366.00000011920929,"x":352.95000457763672,"width":318.10000000000002,"height":36}}],"baseLayer":{"animations":[],"initialState":{"affineTransform":[1,0,0,1,0,0],"masksToBounds":false,"rotation":0,"scale":1,"position":{"pointX":512,"pointY":384},"width":1024,"sublayerTransform":[1,0,0,0,0,1,0,0,0,0,1,0,0,0,0,1],"contentsRect":{"y":0,"x":0,"width":1,"height":1},"opacity":1,"edgeAntialiasingMask":251658240,"height":768,"hidden":false,"anchorPoint":{"pointX":0.5,"pointY":0.5}},"objectID":"0","layers":[{"animations":[],"initialState":{"affineTransform":[1,0,0,1,0,0],"masksToBounds":false,"rotation":0,"scale":1,"position":{"pointX":512,"pointY":384},"width":1024,"sublayerTransform":[1,0,0,0,0,1,0,0,0,0,1,-0.00049229876906403734,0,0,0,1],"contentsRect":{"y":0,"x":0,"width":1,"height":1},"opacity":1,"edgeAntialiasingMask":251658240,"height":768,"hidden":false,"anchorPoint":{"pointX":0.5,"pointY":0.5}},"layers":[{"animations":[],"layers":[],"texturedRectangle":{"isBackgroundTexture":false,"singleTextureOpacity":1,"textureType":0,"textBaseline":0,"textXHeight":0,"isVerticalText":false},"initialState":{"affineTransform":[1,0,0,1,0,0],"masksToBounds":false,"rotation":0,"scale":1,"position":{"pointX":512,"pointY":384},"width":1024,"sublayerTransform":[1,0,0,0,0,1,0,0,0,0,1,0,0,0,0,1],"contentsRect":{"y":0,"x":0,"width":1,"height":1},"opacity":1,"edgeAntialiasingMask":0,"height":768,"hidden":false,"anchorPoint":{"pointX":0.5,"pointY":0.5}},"texture":"085A49673D7C8714419088366BDA5601"}]}]}}]}